project_finance/__init__.py
project_finance/finance.py
tyba_financial_model-0.1.2.dist-info/WHEEL
tyba_financial_model-0.1.2.dist-info/METADATA
tyba_financial_model-0.1.2.dist-info/RECORD
