Metadata-Version: 2.1
Name: tyba-financial-model
Version: 0.1.2
Summary: 
Author: Casey Zak
Author-email: czak24@gmail.com
Requires-Python: >=3.8,<4.0
Classifier: Programming Language :: Python :: 3
Classifier: Programming Language :: Python :: 3.8
Classifier: Programming Language :: Python :: 3.9
Classifier: Programming Language :: Python :: 3.10
Classifier: Programming Language :: Python :: 3.11
Requires-Dist: numpy (>=1.24.1,<2.0.0)
Requires-Dist: pydantic (>=1.10.4,<2.0.0)
